filebrowser_client/__init__.py
filebrowser_client/client.py
filebrowser_client/main.py
filebrowser_client/version.py
filebrowser_client-0.1.0.dist-info/entry_points.txt
filebrowser_client-0.1.0.dist-info/WHEEL
filebrowser_client-0.1.0.dist-info/METADATA
filebrowser_client-0.1.0.dist-info/RECORD
