Metadata-Version: 2.1
Name: filebrowser-client
Version: 0.1.0
Summary: An async CLI client and library for filebrowser API
Home-page: https://github.com/chermed/filebrowser-client
License: MIT
Keywords: filebrowser,cli,client,asyncio
Author: Mohamed CHERKAOUI
Author-email: chermed@gmail.com
Maintainer: Mohamed CHERKAOUI
Maintainer-email: chermed@gmail.com
Requires-Python: >=3.7.2,<4.0
Classifier: Development Status :: 5 - Production/Stable
Classifier: Environment :: Console
Classifier: Intended Audience :: End Users/Desktop
Classifier: Intended Audience :: System Administrators
Classifier: License :: OSI Approved :: MIT License
Classifier: Operating System :: OS Independent
Classifier: Programming Language :: Python :: 3
Classifier: Programming Language :: Python :: 3.8
Classifier: Programming Language :: Python :: 3.9
Classifier: Programming Language :: Python :: 3.10
Classifier: Programming Language :: Python :: 3.11
Classifier: Programming Language :: Python :: 3.7
Classifier: Programming Language :: Python :: 3.8
Classifier: Topic :: System :: Filesystems
Classifier: Topic :: Utilities
Requires-Dist: aiohttp[speedups] (>=3.8.3,<4.0.0)
Requires-Dist: colorama (>=0.4.6,<0.5.0)
Requires-Dist: fire (>=0.4.0,<0.5.0)
Project-URL: Documentation, https://github.com/chermed/filebrowser-client
Project-URL: Repository, https://github.com/chermed/filebrowser-client
